a2p/__init__.py
a2p/client.py
a2p/types.py
a2p/core/__init__.py
a2p/core/consent.py
a2p/core/profile.py
a2p/core/proposal.py
a2p/storage/__init__.py
a2p/storage/cloud.py
a2p/storage/memory.py
a2p/storage/solid.py
a2p/utils/__init__.py
a2p/utils/id.py
a2p/utils/scope.py
a2p_sdk-0.1.3.dist-info/METADATA
a2p_sdk-0.1.3.dist-info/WHEEL
a2p_sdk-0.1.3.dist-info/RECORD
