Metadata-Version: 2.4
Name: a2p-sdk
Version: 0.1.3
Summary: Python SDK for the a2p (Agent 2 Profile) protocol
Project-URL: Homepage, https://alpibrusl.github.io/a2p-protocol
Project-URL: Documentation, https://alpibrusl.github.io/a2p-protocol
Project-URL: Repository, https://github.com/alpibrusl/a2p-protocol
Project-URL: Issues, https://github.com/alpibrusl/a2p-protocol/issues
Author: a2p Protocol Team
License-Expression: EUPL-1.2
Keywords: a2p,agent,ai,consent,decentralized,did,memory,profile,protocol
Classifier: Development Status :: 3 - Alpha
Classifier: Intended Audience :: Developers
Classifier: License :: OSI Approved :: European Union Public Licence 1.2 (EUPL 1.2)
Classifier: Operating System :: OS Independent
Classifier: Programming Language :: Python :: 3
Classifier: Programming Language :: Python :: 3.10
Classifier: Programming Language :: Python :: 3.11
Classifier: Programming Language :: Python :: 3.12
Classifier: Topic :: Software Development :: Libraries :: Python Modules
Classifier: Typing :: Typed
Requires-Python: >=3.10
Requires-Dist: httpx>=0.25.0
Requires-Dist: pydantic>=2.0.0
Provides-Extra: dev
Requires-Dist: mypy>=1.0.0; extra == 'dev'
Requires-Dist: pytest-asyncio>=0.21.0; extra == 'dev'
Requires-Dist: pytest-cov>=4.1.0; extra == 'dev'
Requires-Dist: pytest>=7.0.0; extra == 'dev'
Requires-Dist: ruff>=0.1.0; extra == 'dev'
